{
    "bridge": {
        "name": "Homebridge",
        "username": "CC:22:3D:E3:CE:30",
        "port": 51826,
        "pin": "031-45-154"
    },
    "description": "This is a sample configuration file showing the capabilities of Http-SecuritySystem",
    "accessories": [
        {
            "accessory": "Http-SecuritySystem",
            "name": "Home security",
            "username": "",
            "password": "",
            "immediately": false,
            "polling": true,
            "pollInterval": 30000,
            "http_method": "POST",
            "urls": {
                "stay": { "url": "http://localhost:1880/alarm/arm", "body": "stay" },
                "away": { "url": "http://localhost:1880/alarm/arm", "body": "away" },
                "night": { "url": "http://localhost:1880/alarm/arm", "body": "night" },
                "disarm": { "url": "http://localhost:1880/alarm/disarm", "body": "" },
                "readCurrentState": { "url": "http://localhost:1880/alarm/check", "body": "" },
                "readTargetState": {
                    "url": "http://localhost:1880/alarm/check",
                    "body": "",
                    "headers": {
                        "Content-Type": "application/json"
                    }
                }
            },
            "mappers": [
                {
                    "type": "xpath",
                    "parameters": {
                        "xpath": "//partition[3]/text()"
                    }
                },
                {
                    "type": "regex",
                    "parameters": {
                        "regexp": "^The system is currently (ARMED|DISARMED), yo!$",
                        "capture": "1"
                    }
                },
                {
                    "type": "static",
                    "parameters": {
                        "mapping": {
                            "ARMED": "0",
                            "DISARMED": "3"
                        }
                    }
                }
            ]
        }
    ]
}
